[{"v":1,"t":"To the chief Musician{H5329}{(H8764)} upon Aijeleth{H365} Shahar{H7837}, A Psalm{H4210} of David{H1732}. My God{H410}, my God{H410}, why hast thou forsaken{H5800}{(H8804)} me? why art thou so far{H7350} from helping{H3444} me, and from the words{H1697} of my roaring{H7581}?","c":[],"s":["H365","H410","H1697","H1732","H3444","H4210","H5329","H5800","H7350","H7581","H7837","H8764","H8804"]},{"v":2,"t":"O my God{H430}, I cry{H7121}{(H8799)} in the daytime{H3119}, but thou hearest{H6030}{(H8799)} not; and in the night season{H3915}, and am not silent{H1747}.","c":[],"s":["H430","H1747","H3119","H3915","H6030","H7121","H8799"]},{"v":3,"t":"But thou art holy{H6918}, O thou that inhabitest{H3427}{(H8802)} the praises{H8416} of Israel{H3478}.","c":[],"s":["H3427","H3478","H6918","H8416","H8802"]},{"v":4,"t":"Our fathers{H1} trusted{H982}{(H8804)} in thee: they trusted{H982}{(H8804)}, and thou didst deliver{H6403}{(H8762)} them.","c":[],"s":["H1","H982","H6403","H8762","H8804"]},{"v":5,"t":"They cried{H2199}{(H8804)} unto thee, and were delivered{H4422}{(H8738)}: they trusted{H982}{(H8804)} in thee, and were not confounded{H954}{(H8804)}.","c":[],"s":["H954","H982","H2199","H4422","H8738","H8804"]},{"v":6,"t":"But I am a worm{H8438}, and no man{H376}; a reproach{H2781} of men{H120}, and despised{H959}{(H8803)} of the people{H5971}.","c":[],"s":["H120","H376","H959","H2781","H5971","H8438","H8803"]},{"v":7,"t":"All they that see{H7200}{(H8802)} me laugh me to scorn{H3932}{(H8686)}: they shoot out{H6358}{(H8686)} the lip{H8193}, they shake{H5128}{(H8686)} the head{H7218}, saying,","c":[],"s":["H3932","H5128","H6358","H7200","H7218","H8193","H8686","H8802"]},{"v":8,"t":"He trusted{H1556}{(H8800)} on the LORD{H3068} that he would deliver{H6403}{(H8762)} him: let him deliver{H5337}{(H8686)} him, seeing he delighted{H2654}{(H8804)} in him.","c":[],"s":["H1556","H2654","H3068","H5337","H6403","H8686","H8762","H8800","H8804"]},{"v":9,"t":"But thou art he that took{H1518}{(H8801)} me out of the womb{H990}: thou didst make me hope{H982}{(H8688)} when I was upon my mother's{H517} breasts{H7699}.","c":[],"s":["H517","H982","H990","H1518","H7699","H8688","H8801"]},{"v":10,"t":"I was cast{H7993}{(H8717)} upon thee from the womb{H7358}: thou art my God{H410} from my mother's{H517} belly{H990}.","c":[],"s":["H410","H517","H990","H7358","H7993","H8717"]},{"v":11,"t":"Be not far{H7368}{(H8799)} from me; for trouble{H6869} is near{H7138}; for there is none to help{H5826}{(H8802)}.","c":[],"s":["H5826","H6869","H7138","H7368","H8799","H8802"]},{"v":12,"t":"Many{H7227} bulls{H6499} have compassed{H5437}{(H8804)} me: strong{H47} bulls of Bashan{H1316} have beset me round{H3803}{(H8765)}.","c":[],"s":["H47","H1316","H3803","H5437","H6499","H7227","H8765","H8804"]},{"v":13,"t":"They gaped{H6475}{(H8804)} upon me with their mouths{H6310}, as a ravening{H2963}{(H8802)} and a roaring{H7580}{(H8802)} lion{H738}.","c":[],"s":["H738","H2963","H6310","H6475","H7580","H8802","H8804"]},{"v":14,"t":"I am poured out{H8210}{(H8738)} like water{H4325}, and all my bones{H6106} are out of joint{H6504}{(H8694)}: my heart{H3820} is like wax{H1749}; it is melted{H4549}{(H8738)} in the midst{H8432} of my bowels{H4578}.","c":[],"s":["H1749","H3820","H4325","H4549","H4578","H6106","H6504","H8210","H8432","H8694","H8738"]},{"v":15,"t":"My strength{H3581} is dried up{H3001}{(H8804)} like a potsherd{H2789}; and my tongue{H3956} cleaveth{H1692}{(H8716)} to my jaws{H4455}; and thou hast brought{H8239}{(H8799)} me into the dust{H6083} of death{H4194}.","c":[],"s":["H1692","H2789","H3001","H3581","H3956","H4194","H4455","H6083","H8239","H8716","H8799","H8804"]},{"v":16,"t":"For dogs{H3611} have compassed{H5437}{(H8804)} me: the assembly{H5712} of the wicked{H7489}{(H8688)} have inclosed{H5362}{(H8689)} me: they pierced{H3738}{(H8804)}{(H8675)}{H738} my hands{H3027} and my feet{H7272}.","c":[],"s":["H738","H3027","H3611","H3738","H5362","H5437","H5712","H7272","H7489","H8675","H8688","H8689","H8804"]},{"v":17,"t":"I may tell{H5608}{(H8762)} all my bones{H6106}: they look{H5027}{(H8686)} and stare{H7200}{(H8799)} upon me.","c":[],"s":["H5027","H5608","H6106","H7200","H8686","H8762","H8799"]},{"v":18,"t":"They part{H2505}{(H8762)} my garments{H899} among them, and cast{H5307}{(H8686)} lots{H1486} upon my vesture{H3830}.","c":[],"s":["H899","H1486","H2505","H3830","H5307","H8686","H8762"]},{"v":19,"t":"But be not thou far{H7368}{(H8799)} from me, O LORD{H3068}: O my strength{H360}, haste{H2363}{(H8798)} thee to help{H5833} me.","c":[],"s":["H360","H2363","H3068","H5833","H7368","H8798","H8799"]},{"v":20,"t":"Deliver{H5337}{(H8685)} my soul{H5315} from the sword{H2719}; my darling{H3173} from the power{H3027} of the dog{H3611}.","c":[],"s":["H2719","H3027","H3173","H3611","H5315","H5337","H8685"]},{"v":21,"t":"Save{H3467}{(H8685)} me from the lion's{H738} mouth{H6310}: for thou hast heard{H6030}{(H8804)} me from the horns{H7161} of the unicorns{H7214}.","c":[],"s":["H738","H3467","H6030","H6310","H7161","H7214","H8685","H8804"]},{"v":22,"t":"I will declare{H5608}{(H8762)} thy name{H8034} unto my brethren{H251}: in the midst{H8432} of the congregation{H6951} will I praise{H1984}{(H8762)} thee.","c":[],"s":["H251","H1984","H5608","H6951","H8034","H8432","H8762"]},{"v":23,"t":"Ye that fear{H3373} the LORD{H3068}, praise{H1984}{(H8761)} him; all ye the seed{H2233} of Jacob{H3290}, glorify{H3513}{(H8761)} him; and fear{H1481}{(H8798)} him, all ye the seed{H2233} of Israel{H3478}.","c":[],"s":["H1481","H1984","H2233","H3068","H3290","H3373","H3478","H3513","H8761","H8798"]},{"v":24,"t":"For he hath not despised{H959}{(H8804)} nor abhorred{H8262}{(H8765)} the affliction{H6039} of the afflicted{H6041}; neither hath he hid{H5641}{(H8689)} his face{H6440} from him; but when he cried{H7768}{(H8763)} unto him, he heard{H8085}{(H8804)}.","c":[],"s":["H959","H5641","H6039","H6041","H6440","H7768","H8085","H8262","H8689","H8763","H8765","H8804"]},{"v":25,"t":"My praise{H8416} shall be of thee in the great{H7227} congregation{H6951}: I will pay{H7999}{(H8762)} my vows{H5088} before them that fear{H3373} him.","c":[],"s":["H3373","H5088","H6951","H7227","H7999","H8416","H8762"]},{"v":26,"t":"The meek{H6035} shall eat{H398}{(H8799)} and be satisfied{H7646}{(H8799)}: they shall praise{H1984}{(H8762)} the LORD{H3068} that seek{H1875}{(H8802)} him: your heart{H3824} shall live{H2421}{(H8799)} for ever{H5703}.","c":[],"s":["H398","H1875","H1984","H2421","H3068","H3824","H5703","H6035","H7646","H8762","H8799","H8802"]},{"v":27,"t":"All the ends{H657} of the world{H776} shall remember{H2142}{(H8799)} and turn{H7725}{(H8799)} unto the LORD{H3068}: and all the kindreds{H4940} of the nations{H1471} shall worship{H7812}{(H8691)} before{H6440} thee.","c":[],"s":["H657","H776","H1471","H2142","H3068","H4940","H6440","H7725","H7812","H8691","H8799"]},{"v":28,"t":"For the kingdom{H4410} is the LORD'S{H3068}: and he is the governor{H4910}{(H8802)} among the nations{H1471}.","c":[],"s":["H1471","H3068","H4410","H4910","H8802"]},{"v":29,"t":"All they that be fat{H1879} upon earth{H776} shall eat{H398}{(H8804)} and worship{H7812}{(H8691)}: all they that go down{H3381}{(H8802)} to the dust{H6083} shall bow{H3766}{(H8799)} before{H6440} him: and none can keep alive{H2421}{(H8765)} his own soul{H5315}.","c":[],"s":["H398","H776","H1879","H2421","H3381","H3766","H5315","H6083","H6440","H7812","H8691","H8765","H8799","H8802","H8804"]},{"v":30,"t":"A seed{H2233} shall serve{H5647}{(H8799)} him; it shall be accounted{H5608}{(H8792)} to the Lord{H136} for a generation{H1755}.","c":[],"s":["H136","H1755","H2233","H5608","H5647","H8792","H8799"]},{"v":31,"t":"They shall come{H935}{(H8799)}, and shall declare{H5046}{(H8686)} his righteousness{H6666} unto a people{H5971} that shall be born{H3205}{(H8737)}, that he hath done{H6213}{(H8804)} this.","c":[],"s":["H935","H3205","H5046","H5971","H6213","H6666","H8686","H8737","H8799","H8804"]}]