[
  {
    "v": 1,
    "t": "To the chief Musician{H5329}{H8764)} upon Shushaneduth{H7802}, Michtam{H4387} of David{H1732}, to teach{H3925}{H8763)}; when he strove{H5327}{H8687)} with Aramnaharaim{H763}{H5104} and with Aramzobah{H760}, when Joab{H3097} returned{H7725}{H8799)}, and smote{H5221}{H8686)} of Edom{H123} in the valley{H1516} of salt{H4417} twelve{H8147}{H6240} thousand{H505}. O God{H430}, thou hast cast us off{H2186}{H8804)}, thou hast scattered{H6555}{H8804)} us, thou hast been displeased{H599}{H8804)}; O turn thyself to us again{H7725}{H8787)}.",
    "c": [
      "1 Chronicles 19:16",
      "1 Chronicles 19:17",
      "1 Chronicles 19:18",
      "1 Chronicles 19:19",
      "Psalms 108:11",
      "1 Samuel 4:17",
      "2 Samuel 5:20",
      "Psalms 90:13",
      "1 Chronicles 28:9",
      "2 Samuel 8:3",
      "Psalms 74:1",
      "1 Samuel 31:1",
      "1 Samuel 31:2",
      "1 Samuel 31:3",
      "1 Samuel 31:4",
      "1 Samuel 31:5",
      "1 Samuel 31:6",
      "1 Samuel 31:7",
      "1 Chronicles 18:12",
      "1 Chronicles 18:13",
      "1 Samuel 4:10",
      "1 Samuel 4:11",
      "Psalms 79:5",
      "2 Kings 14:7",
      "Psalms 59:11",
      "Psalms 89:3",
      "Psalms 44:9",
      "1 Samuel 13:19",
      "1 Samuel 13:20",
      "1 Samuel 13:21",
      "1 Samuel 13:22",
      "Psalms 79:9",
      "Psalms 85:4",
      "1 Samuel 13:6",
      "1 Samuel 13:7",
      "Psalms 60:10",
      "Psalms 89:38",
      "2 Samuel 8:12",
      "2 Samuel 8:13",
      "Psalms 89:7",
      "Zechariah 10:6",
      "2 Samuel 10:16",
      "Psalms 89:19",
      "Romans 11:1",
      "Romans 11:2",
      "2 Chronicles 25:11",
      "Lamentations 3:31",
      "Lamentations 3:32",
      "1 Chronicles 18:3",
      "Psalms 80:3",
      "Psalms 59:1",
      "1 Samuel 13:11"
    ],
    "s": [
      "H123",
      "H430",
      "H505",
      "H599",
      "H760",
      "H763",
      "H1516",
      "H1732",
      "H2186",
      "H3097",
      "H3925",
      "H4387",
      "H4417",
      "H5104",
      "H5221",
      "H5327",
      "H5329",
      "H6240",
      "H6555",
      "H7725",
      "H7802",
      "H8147",
      "H8686",
      "H8687",
      "H8763",
      "H8764",
      "H8787",
      "H8799",
      "H8804"
    ]
  },
  {
    "v": 2,
    "t": "Thou hast made the earth{H776} to tremble{H7493}{H8689)}; thou hast broken{H6480}{H8804)} it: heal{H7495}{H8798)} the breaches{H7667} thereof; for it shaketh{H4131}{H8804)}.",
    "c": [
      "Jeremiah 4:24",
      "Isaiah 30:26",
      "Jeremiah 30:17",
      "Isaiah 5:25",
      "2 Samuel 3:11",
      "2 Samuel 3:12",
      "2 Samuel 3:13",
      "2 Samuel 3:14",
      "Ezekiel 34:16",
      "Jeremiah 48:38",
      "2 Samuel 22:8",
      "Matthew 27:51",
      "Amos 8:8",
      "Job 9:6",
      "Lamentations 2:13",
      "Jeremiah 10:10",
      "Isaiah 7:8",
      "Psalms 18:7",
      "Psalms 89:40",
      "2 Samuel 2:8",
      "2 Samuel 2:9",
      "2 Samuel 2:10",
      "2 Samuel 2:11",
      "2 Samuel 2:12",
      "2 Samuel 2:13",
      "2 Samuel 2:14",
      "2 Samuel 2:15",
      "2 Samuel 2:16",
      "2 Samuel 2:17",
      "2 Samuel 2:18",
      "2 Samuel 2:19",
      "2 Samuel 2:20",
      "2 Samuel 2:21",
      "2 Samuel 2:22",
      "2 Samuel 2:23",
      "2 Samuel 2:24",
      "2 Samuel 2:25",
      "2 Samuel 2:26",
      "2 Samuel 2:27",
      "2 Samuel 2:28",
      "2 Samuel 2:29",
      "2 Samuel 2:30",
      "2 Samuel 2:31",
      "2 Samuel 2:32",
      "Hosea 6:1",
      "Psalms 104:32",
      "Habakkuk 3:10",
      "Jeremiah 14:17",
      "Haggai 2:6",
      "Haggai 2:7",
      "Psalms 114:7",
      "2 Chronicles 7:14",
      "Job 5:18"
    ],
    "s": [
      "H776",
      "H4131",
      "H6480",
      "H7493",
      "H7495",
      "H7667",
      "H8689",
      "H8798",
      "H8804"
    ]
  },
  {
    "v": 3,
    "t": "Thou hast shewed{H7200}{H8689)} thy people{H5971} hard things{H7186}: thou hast made us to drink{H8248}{H8689)} the wine{H3196} of astonishment{H8653}.",
    "c": [
      "Ezekiel 23:31",
      "Ezekiel 23:32",
      "Jeremiah 25:15",
      "Isaiah 51:22",
      "Daniel 9:12",
      "Lamentations 4:21",
      "Revelation 18:16",
      "Habakkuk 2:16",
      "Psalms 75:8",
      "Revelation 16:19",
      "Nehemiah 9:32",
      "Psalms 71:20",
      "Isaiah 51:17"
    ],
    "s": [
      "H3196",
      "H5971",
      "H7186",
      "H7200",
      "H8248",
      "H8653",
      "H8689"
    ]
  },
  {
    "v": 4,
    "t": "Thou hast given{H5414}{H8804)} a banner{H5251} to them that fear{H3373} thee, that it may be displayed{H5127}{H8710)} because{H6440} of the truth{H7189}. Selah{H5542}.",
    "c": [
      "Psalms 20:5",
      "Isaiah 13:2",
      "Isaiah 59:19",
      "Isaiah 11:12",
      "Psalms 45:4",
      "Isaiah 49:22",
      "Jeremiah 5:1",
      "Jeremiah 5:2",
      "Jeremiah 5:3",
      "Psalms 12:1",
      "Psalms 12:2",
      "Exodus 17:15",
      "Isaiah 59:14",
      "Isaiah 59:15",
      "Song of Solomon 2:4",
      "Isaiah 5:26"
    ],
    "s": [
      "H3373",
      "H5127",
      "H5251",
      "H5414",
      "H5542",
      "H6440",
      "H7189",
      "H8710",
      "H8804"
    ]
  },
  {
    "v": 5,
    "t": "That thy beloved{H3039} may be delivered{H2502}{H8735)}; save{H3467}{H8685)} with thy right hand{H3225}, and hear{H6030}{H8798)} me.",
    "c": [
      "Matthew 3:17",
      "Psalms 108:6",
      "Psalms 108:7",
      "Psalms 108:8",
      "Psalms 108:9",
      "Psalms 108:10",
      "Psalms 108:11",
      "Psalms 108:12",
      "Psalms 108:13",
      "Psalms 22:8",
      "Psalms 127:2",
      "Isaiah 41:10",
      "Matthew 17:5",
      "Psalms 18:35",
      "Psalms 17:7",
      "Psalms 74:11",
      "Deuteronomy 7:7",
      "Deuteronomy 7:8",
      "Exodus 15:6",
      "Deuteronomy 33:3",
      "Deuteronomy 33:12",
      "Psalms 20:6",
      "Jeremiah 11:15",
      "Psalms 60:12"
    ],
    "s": [
      "H2502",
      "H3039",
      "H3225",
      "H3467",
      "H6030",
      "H8685",
      "H8735",
      "H8798"
    ]
  },
  {
    "v": 6,
    "t": "God{H430} hath spoken{H1696}{H8765)} in his holiness{H6944}; I will rejoice{H5937}{H8799)}, I will divide{H2505}{H8762)} Shechem{H7927}, and mete out{H4058}{H8762)} the valley{H6010} of Succoth{H5523}.",
    "c": [
      "Jeremiah 23:9",
      "Psalms 56:4",
      "Genesis 33:17",
      "Genesis 33:18",
      "2 Samuel 7:18",
      "2 Samuel 7:19",
      "2 Samuel 7:20",
      "Joshua 13:27",
      "Psalms 132:11",
      "Joshua 24:32",
      "Psalms 89:19",
      "2 Samuel 2:8",
      "2 Samuel 2:9",
      "Joshua 1:6",
      "Amos 4:2",
      "Joshua 24:1",
      "Psalms 119:162",
      "Joshua 20:7",
      "Genesis 12:6",
      "Psalms 89:35",
      "Joshua 17:7",
      "Luke 1:45",
      "Luke 1:46",
      "Luke 1:47",
      "Psalms 108:7",
      "Psalms 108:8",
      "Psalms 108:9",
      "Psalms 108:10",
      "Psalms 108:11",
      "Psalms 108:12",
      "Psalms 108:13",
      "2 Samuel 5:1",
      "2 Samuel 5:2",
      "2 Samuel 5:3",
      "2 Samuel 3:18"
    ],
    "s": [
      "H430",
      "H1696",
      "H2505",
      "H4058",
      "H5523",
      "H5937",
      "H6010",
      "H6944",
      "H7927",
      "H8762",
      "H8765",
      "H8799"
    ]
  },
  {
    "v": 7,
    "t": "Gilead{H1568} is mine, and Manasseh{H4519} is mine; Ephraim{H669} also is the strength{H4581} of mine head{H7218}; Judah{H3063} is my lawgiver{H2710}{H8781)};",
    "c": [
      "1 Chronicles 12:37",
      "Deuteronomy 33:17",
      "1 Chronicles 12:19",
      "Genesis 49:10",
      "1 Samuel 28:2",
      "Joshua 17:1",
      "Joshua 17:5",
      "Joshua 17:6",
      "Joshua 13:31"
    ],
    "s": [
      "H669",
      "H1568",
      "H2710",
      "H3063",
      "H4519",
      "H4581",
      "H7218",
      "H8781"
    ]
  },
  {
    "v": 8,
    "t": "Moab{H4124} is my washpot{H5518}{H7366}; over Edom{H123} will I cast out{H7993}{H8686)} my shoe{H5275}: Philistia{H6429}, triumph{H7321}{H8708)} thou because of me.",
    "c": [
      "Genesis 27:40",
      "1 Chronicles 18:13",
      "Numbers 24:18",
      "2 Samuel 8:14",
      "2 Samuel 21:15",
      "2 Samuel 21:16",
      "2 Samuel 21:17",
      "2 Samuel 21:18",
      "2 Samuel 21:19",
      "2 Samuel 21:20",
      "2 Samuel 21:21",
      "2 Samuel 21:22",
      "2 Samuel 8:1",
      "2 Samuel 8:2",
      "Psalms 108:9",
      "Psalms 108:10",
      "Genesis 25:23",
      "1 Chronicles 18:1",
      "1 Chronicles 18:2",
      "2 Samuel 5:17",
      "2 Samuel 5:18",
      "2 Samuel 5:19",
      "2 Samuel 5:20",
      "2 Samuel 5:21",
      "2 Samuel 5:22",
      "2 Samuel 5:23",
      "2 Samuel 5:24",
      "2 Samuel 5:25"
    ],
    "s": [
      "H123",
      "H4124",
      "H5275",
      "H5518",
      "H6429",
      "H7321",
      "H7366",
      "H7993",
      "H8686",
      "H8708"
    ]
  },
  {
    "v": 9,
    "t": "Who will bring{H2986}{H8686)} me into the strong{H4692} city{H5892}? who will lead{H5148}{H8804)} me into Edom{H123}?",
    "c": [
      "2 Samuel 11:1",
      "2 Samuel 12:26",
      "2 Samuel 12:27",
      "2 Samuel 12:28",
      "2 Samuel 12:29",
      "2 Samuel 12:30",
      "2 Samuel 12:31",
      "Judges 1:24",
      "Judges 1:25",
      "1 Chronicles 11:17",
      "1 Chronicles 11:18",
      "1 Chronicles 11:19",
      "Judges 1:12",
      "1 Chronicles 11:6"
    ],
    "s": [
      "H123",
      "H2986",
      "H4692",
      "H5148",
      "H5892",
      "H8686",
      "H8804"
    ]
  },
  {
    "v": 10,
    "t": "Wilt not thou, O God{H430}, which hadst cast us off{H2186}{H8804)}? and thou, O God{H430}, which didst not go out{H3318}{H8799)} with our armies{H6635}?",
    "c": [
      "Deuteronomy 1:42",
      "Psalms 108:11",
      "Joshua 7:12",
      "1 Samuel 4:10",
      "1 Samuel 4:11",
      "Isaiah 12:1",
      "Isaiah 12:2",
      "1 Samuel 4:6",
      "1 Samuel 4:7",
      "Jeremiah 33:24",
      "Jeremiah 33:25",
      "Jeremiah 33:26",
      "Psalms 60:1",
      "Psalms 118:9",
      "Psalms 118:10",
      "Joshua 10:42",
      "Deuteronomy 20:4",
      "Isaiah 8:17",
      "1 Chronicles 10:1",
      "1 Chronicles 10:2",
      "1 Chronicles 10:3",
      "1 Chronicles 10:4",
      "1 Chronicles 10:5",
      "1 Chronicles 10:6",
      "1 Chronicles 10:7",
      "1 Chronicles 10:8",
      "1 Chronicles 10:9",
      "1 Chronicles 10:10",
      "1 Chronicles 10:11",
      "1 Chronicles 10:12",
      "1 Chronicles 10:13",
      "1 Chronicles 10:14",
      "Psalms 20:7",
      "Psalms 44:5",
      "Psalms 44:6",
      "Psalms 44:7",
      "Psalms 44:8",
      "Psalms 44:9"
    ],
    "s": [
      "H430",
      "H2186",
      "H3318",
      "H6635",
      "H8799",
      "H8804"
    ]
  },
  {
    "v": 11,
    "t": "Give{H3051}{H8798)} us help{H5833} from trouble{H6862}: for vain{H7723} is the help{H8668} of man{H120}.",
    "c": [
      "Psalms 25:22",
      "Isaiah 31:3",
      "Psalms 130:8",
      "Psalms 62:1",
      "Psalms 124:1",
      "Psalms 124:2",
      "Psalms 124:3",
      "Psalms 146:3",
      "Isaiah 30:7",
      "Psalms 108:12"
    ],
    "s": [
      "H120",
      "H3051",
      "H5833",
      "H6862",
      "H7723",
      "H8668",
      "H8798"
    ]
  },
  {
    "v": 12,
    "t": "Through God{H430} we shall do{H6213}{H8799)} valiantly{H2428}: for he it is that shall tread down{H947}{H8799)} our enemies{H6862}.",
    "c": [
      "Isaiah 10:6",
      "Revelation 19:15",
      "Joshua 1:9",
      "2 Samuel 10:12",
      "1 Chronicles 19:13",
      "Psalms 44:5",
      "Numbers 24:18",
      "Numbers 24:19",
      "Zechariah 10:5",
      "Joshua 14:12",
      "Isaiah 63:3",
      "Malachi 4:3",
      "Psalms 144:1",
      "Psalms 18:32",
      "Psalms 18:33",
      "Psalms 18:34",
      "Psalms 18:35",
      "Psalms 18:36",
      "Psalms 18:37",
      "Psalms 18:38",
      "Psalms 18:39",
      "Psalms 18:40",
      "Psalms 18:41",
      "Psalms 18:42",
      "Psalms 118:16"
    ],
    "s": [
      "H430",
      "H947",
      "H2428",
      "H6213",
      "H6862",
      "H8799"
    ]
  }
]